jxl_decode/__init__.py
jxl_decode/__main__.py
jxl_decode/common.py
jxl_decode/decode_jpg.py
jxl_decode/decode_jxl.py
jxl_decode/decode_ppm.py
jxl_decode/encode_png.py
jxl_decode/main.py
jxl_decode-0.0.2.dist-info/LICENCE.md
jxl_decode-0.0.2.dist-info/METADATA
jxl_decode-0.0.2.dist-info/WHEEL
jxl_decode-0.0.2.dist-info/top_level.txt
jxl_decode-0.0.2.dist-info/RECORD
