Metadata-Version: 2.1
Name: jxl-decode
Version: 0.0.2
Summary: A pure python JPEG XL decoder.
Author-email: James Frost <git@frost.cx>
Project-URL: Homepage, https://github.com/Fraetor/jxl_decode
Project-URL: Bug Tracker, https://github.com/Fraetor/jxl_decode/issues
Keywords: JPEG XL,jxl
Classifier: Programming Language :: Python :: 3
Classifier: License :: OSI Approved :: MIT License
Classifier: Operating System :: OS Independent
Classifier: Development Status :: 2 - Pre-Alpha
Classifier: Topic :: Multimedia :: Graphics
Requires-Python: >=3.10
License-File: LICENCE.md
